drtodo/README.md
drtodo/__init__.py
drtodo/__main__.py
drtodo/backup_command.py
drtodo/config.py
drtodo/main.py
drtodo/man/README.md
drtodo/man/__init__.py
drtodo/man/config.md
drtodo/man/intro.md
drtodo/man/mdfiles.md
drtodo/man_command.py
drtodo/mdparser.py
drtodo/mistuneplugin.py
drtodo/rich_display.py
drtodo/taskitems.py
drtodo/util.py
typer_aliases/__init__.py
typer_aliases/core.py
drtodo-0.6.12.dist-info/LICENSE
drtodo-0.6.12.dist-info/METADATA
drtodo-0.6.12.dist-info/WHEEL
drtodo-0.6.12.dist-info/entry_points.txt
drtodo-0.6.12.dist-info/RECORD
