Metadata-Version: 2.1
Name: DrToDo
Version: 0.6.12
Summary: DrToDo, MD: todo list manager using markdown files and git
Home-page: https://github.com/exilium-com/DrTodo
License: MIT
Keywords: utilities,todo,markdown
Author: exilium
Author-email: info@exilium.com
Requires-Python: >=3.9,<4.0
Classifier: License :: OSI Approved :: MIT License
Classifier: Programming Language :: Python :: 3
Classifier: Programming Language :: Python :: 3.9
Classifier: Programming Language :: Python :: 3.10
Classifier: Programming Language :: Python :: 3.11
Classifier: Programming Language :: Python :: 3.12
Requires-Dist: gitpython (>=3.1,<3.2)
Requires-Dist: mistune (==3.0.2)
Requires-Dist: pydantic (>=1.10,<1.11)
Requires-Dist: rich (>=13.4,<13.8)
Requires-Dist: tomli ; python_version < "3.11"
Requires-Dist: typer (>=0.7,<0.13)
Requires-Dist: typing-extensions (>=4.5.0,<5.0.0) ; python_version < "3.11"
Project-URL: Repository, https://github.com/exilium-com/DrTodo
